sboannotator/SBOannotator.py
sboannotator/__init__.py
sboannotator/__main__.py
sboannotator/create_dbs.sql
SBOannotator-3.0.4.dist-info/LICENSE
SBOannotator-3.0.4.dist-info/METADATA
SBOannotator-3.0.4.dist-info/WHEEL
SBOannotator-3.0.4.dist-info/top_level.txt
SBOannotator-3.0.4.dist-info/RECORD
