Metadata-Version: 2.1
Name: SBOannotator
Version: 3.0.4
Summary: SBOannotator: A Python tool for the automated assignment of Systems Biology Ontology terms
Home-page: https://github.com/draeger-lab/SBOannotator
Author: Nantia Leonidou, Elisabeth Fritze, Alina Renz, Andreas Dräger
Author-email: nantia.leonidou@uni-tuebingen.de
License: GPL-3.0
Keywords: SBOannotator,SBO Terms,automated tool
Platform: UNKNOWN
Classifier: Programming Language :: Python :: 3.8
Classifier: Programming Language :: Python :: 3.9
Classifier: Programming Language :: Python :: 3.10
Classifier: Topic :: Software Development :: Version Control :: Git
Classifier: Operating System :: MacOS
Classifier: Operating System :: Unix
License-File: LICENSE
Requires-Dist: python-libsbml
Requires-Dist: python-collection
Requires-Dist: requests
Requires-Dist: pypi-json
